jingongo/__init__.py
jingongo/jingongo.py
jingongo_framework-0.1.4.dist-info/licenses/LICENSE
jingongo_framework-0.1.4.dist-info/METADATA
jingongo_framework-0.1.4.dist-info/WHEEL
jingongo_framework-0.1.4.dist-info/top_level.txt
jingongo_framework-0.1.4.dist-info/RECORD
