Metadata-Version: 2.4
Name: jingongo-framework
Version: 0.1.4
Summary: A Python SDK for the Jingongo Digital Twin Framework API.
Author-email: Valdimiro Cussei <valdimiro.cussei@ratotecki.com>, Bento Cussei <bento.cussei@ratotecki.com>
License: Apache-2.0
Project-URL: Homepage, https://github.com/vcussei/jingongo
Project-URL: Repository, https://github.com/vcussei/jingongo
Project-URL: Bug Tracker, https://github.com/vcussei/jingongo/issues
Keywords: fmu,digital twin,simulation,jingongo,fmi
Classifier: Development Status :: 3 - Alpha
Classifier: Intended Audience :: Developers
Classifier: Intended Audience :: Science/Research
Classifier: License :: OSI Approved :: Apache Software License
Classifier: Programming Language :: Python :: 3
Classifier: Programming Language :: Python :: 3.8
Classifier: Programming Language :: Python :: 3.9
Classifier: Programming Language :: Python :: 3.10
Classifier: Programming Language :: Python :: 3.11
Classifier: Operating System :: OS Independent
Classifier: Topic :: Scientific/Engineering
Classifier: Topic :: Software Development :: Libraries :: Python Modules
Requires-Python: >=3.8
License-File: LICENSE
Requires-Dist: requests>=2.20.0
Requires-Dist: PyYAML>=5.0
Requires-Dist: tqdm>=4.60.0
Provides-Extra: test
Requires-Dist: pytest>=7.0.0; extra == "test"
Dynamic: license-file
